koncert/__init__.py
koncert-0.0.1.dist-info/LICENSE
koncert-0.0.1.dist-info/METADATA
koncert-0.0.1.dist-info/WHEEL
koncert-0.0.1.dist-info/top_level.txt
koncert-0.0.1.dist-info/RECORD
