Metadata-Version: 2.1
Name: koncert
Version: 0.0.1
Summary: scraper for NICE Checkplus
Home-page: https://github.com/jiwonMe/KONCERT
Author: Jiwon Park
Author-email: park@jiwon.me
License: UNKNOWN
Platform: UNKNOWN
Classifier: Programming Language :: Python :: 3
Classifier: License :: OSI Approved :: MIT License
Classifier: Operating System :: OS Independent
Requires-Python: >=3.8
